jadoomantar/__init__.py
jadoomantar/main.py
jadoomantar-0.2.dist-info/LICENSE
jadoomantar-0.2.dist-info/METADATA
jadoomantar-0.2.dist-info/WHEEL
jadoomantar-0.2.dist-info/entry_points.txt
jadoomantar-0.2.dist-info/top_level.txt
jadoomantar-0.2.dist-info/RECORD
