Metadata-Version: 2.1
Name: jadoomantar
Version: 0.2
Summary: A package for creating an invisible cloak effect using OpenCV.
Home-page: https://github.com/yourusername/jadoomantar
Author: Your Name
Author-email: your.email@example.com
Classifier: Programming Language :: Python :: 3
Classifier: License :: OSI Approved :: MIT License
Classifier: Operating System :: OS Independent
Requires-Python: >=3.6
License-File: LICENSE
Requires-Dist: opencv-python >=4.5.1
Requires-Dist: numpy >=1.19.5
